[
    {
        "id": "41c93dbf-a7b6-43c2-a7c9-5b8c89a91a45",
        "firstName": "Ahmet",
        "lastName": "Sourtimes",
        "dateOfBirth": "1979-02-19",
        "dateOfEmployment": "2023-11-01",
        "phoneNumber": "286 1 315",
        "email": "ahmet.sourtimes@gmail.com",
        "department": "Tech",
        "position": "Senior"
    },
    {
        "id": "4453c9f6-03b3-4871-9790-ea42db427b49",
        "firstName": "Ahmet",
        "lastName": "Sourtimes",
        "dateOfBirth": "2000-07-31",
        "dateOfEmployment": "2023-11-01",
        "phoneNumber": "0018 759 99 97",
        "email": "ahmet.sourtimes@gmail.com",
        "department": "Analytics",
        "position": "Medior"
    },
    {
        "id": "86d3e9b5-95a9-4793-ad32-a7bfb822a961",
        "firstName": "Ahmet",
        "lastName": "Sourtimes",
        "dateOfBirth": "1979-01-23",
        "dateOfEmployment": "2023-11-01",
        "phoneNumber": "+90(916)161-0992x881",
        "email": "ahmet.sourtimes@gmail.com",
        "department": "Analytics",
        "position": "Junior"
    },
    {
        "id": "c03b16c5-f68d-4c19-a878-5ef0fd8fb3f1",
        "firstName": "Ahmet",
        "lastName": "Sourtimes",
        "dateOfBirth": "1993-05-26",
        "dateOfEmployment": "2023-11-01",
        "phoneNumber": "+90 (179) 3369538",
        "email": "ahmet.sourtimes@gmail.com",
        "department": "Tech",
        "position": "Medior"
    },
    {
        "id": "0155f919-19ed-4aeb-8d6a-a35f1fa01049",
        "firstName": "Ahmet",
        "lastName": "Sourtimes",
        "dateOfBirth": "2001-11-29",
        "dateOfEmployment": "2023-11-01",
        "phoneNumber": "0157 777 31 06",
        "email": "ahmet.sourtimes@gmail.com",
        "department": "Analytics",
        "position": "Medior"
    },
    {
        "id": "c5af2049-2c85-4d6c-8201-03b518af564e",
        "firstName": "Ahmet",
        "lastName": "Sourtimes",
        "dateOfBirth": "1983-06-11",
        "dateOfEmployment": "2023-11-01",
        "phoneNumber": "05943910697",
        "email": "ahmet.sourtimes@gmail.com",
        "department": "Tech",
        "position": "Junior"
    },
    {
        "id": "c5b82ea8-3cf6-4e8b-b701-1e5345a41696",
        "firstName": "Ahmet",
        "lastName": "Sourtimes",
        "dateOfBirth": "1967-06-10",
        "dateOfEmployment": "2023-11-01",
        "phoneNumber": "05084450491",
        "email": "ahmet.sourtimes@gmail.com",
        "department": "Tech",
        "position": "Senior"
    },
    {
        "id": "c5b82ea8-3cf6-4e8b-b701-1e5345a41696",
        "firstName": "Ahmet",
        "lastName": "Sourtimes",
        "dateOfBirth": "1971-12-09",
        "dateOfEmployment": "2023-11-01",
        "phoneNumber": "+90(089)152-8931x9293",
        "email": "ahmet.sourtimes@gmail.com",
        "department": "Tech",
        "position": "Junior"
    },
    {
        "id": "153005b3-99e6-42ef-a0d0-eb0c55196b65",
        "firstName": "Ahmet",
        "lastName": "Sourtimes",
        "dateOfBirth": "1980-07-07",
        "dateOfEmployment": "2023-11-01",
        "phoneNumber": "+90(390)2588005",
        "email": "ahmet.sourtimes@gmail.com",
        "department": "Tech",
        "position": "Senior"
    },
    {
        "id": "83f192a4-248f-4fd7-ab66-5319ee0f8142",
        "firstName": "Ahmet",
        "lastName": "Sourtimes",
        "dateOfBirth": "1995-01-26",
        "dateOfEmployment": "2023-11-01",
        "phoneNumber": "+90 (212) 2047647",
        "email": "ahmet.sourtimes@gmail.com",
        "department": "Tech",
        "position": "Senior"
    },
    {
        "id": "b71f0956-b7bc-443e-83a5-eefbfbc8c27a",
        "firstName": "Ahmet",
        "lastName": "Sourtimes",
        "dateOfBirth": "1969-03-04",
        "dateOfEmployment": "2023-11-01",
        "phoneNumber": "0557 010 35 06",
        "email": "ahmet.sourtimes@gmail.com",
        "department": "Analytics",
        "position": "Senior"
    },
    {
        "id": "1ac7b138-1bfc-4f91-a274-db3f8e16c734",
        "firstName": "Ahmet",
        "lastName": "Sourtimes",
        "dateOfBirth": "1978-01-17",
        "dateOfEmployment": "2023-11-01",
        "phoneNumber": "(696)904 4112",
        "email": "ahmet.sourtimes@gmail.com",
        "department": "Analytics",
        "position": "Senior"
    },
    {
        "id": "a15638fc-d429-4200-8fef-3e2da70e42c7",
        "firstName": "Ahmet",
        "lastName": "Sourtimes",
        "dateOfBirth": "2000-01-18",
        "dateOfEmployment": "2023-11-01",
        "phoneNumber": "+90(711)790-4504x8574",
        "email": "ahmet.sourtimes@gmail.com",
        "department": "Analytics",
        "position": "Medior"
    },
    {
        "id": "829460aa-c4ad-4197-b1b9-28806599ad3f",
        "firstName": "Ahmet",
        "lastName": "Sourtimes",
        "dateOfBirth": "1969-10-03",
        "dateOfEmployment": "2023-11-01",
        "phoneNumber": "03188079563",
        "email": "ahmet.sourtimes@gmail.com",
        "department": "Tech",
        "position": "Senior"
    },
    {
        "id": "2ff56c2f-5415-4eeb-9596-ca1d7fd5c201",
        "firstName": "Ahmet",
        "lastName": "Sourtimes",
        "dateOfBirth": "1996-01-22",
        "dateOfEmployment": "2023-11-01",
        "phoneNumber": "(372)684 0920",
        "email": "ahmet.sourtimes@gmail.com",
        "department": "Analytics",
        "position": "Junior"
    },
    {
        "id": "415b53fa-7898-4fa0-a339-bb8769c4b568",
        "firstName": "Ahmet",
        "lastName": "Sourtimes",
        "dateOfBirth": "1979-10-02",
        "dateOfEmployment": "2023-11-01",
        "phoneNumber": "0706-515 4397",
        "email": "ahmet.sourtimes@gmail.com",
        "department": "Analytics",
        "position": "Senior"
    },
    {
        "id": "3a83f60c-03dc-41ab-a9c0-0ba252b81f46",
        "firstName": "Ahmet",
        "lastName": "Sourtimes",
        "dateOfBirth": "1989-07-24",
        "dateOfEmployment": "2023-11-01",
        "phoneNumber": "00159419539",
        "email": "ahmet.sourtimes@gmail.com",
        "department": "Analytics",
        "position": "Senior"
    },
    {
        "id": "7b65987b-9657-40fc-863c-0c1b44383728",
        "firstName": "Ahmet",
        "lastName": "Sourtimes",
        "dateOfBirth": "1966-05-14",
        "dateOfEmployment": "2023-11-01",
        "phoneNumber": "(540)197 2407",
        "email": "ahmet.sourtimes@gmail.com",
        "department": "Tech",
        "position": "Medior"
    },
    {
        "id": "eff012dc-9916-4ad2-8d2d-562afdf8916b",
        "firstName": "Ahmet",
        "lastName": "Sourtimes",
        "dateOfBirth": "1979-09-04",
        "dateOfEmployment": "2023-11-01",
        "phoneNumber": "07645980853",
        "email": "ahmet.sourtimes@gmail.com",
        "department": "Tech",
        "position": "Medior"
    },
    {
        "id": "45837271-55a4-410d-a895-44b166d122f2",
        "firstName": "Ahmet",
        "lastName": "Sourtimes",
        "dateOfBirth": "1982-08-10",
        "dateOfEmployment": "2023-11-01",
        "phoneNumber": "(832)420 4186",
        "email": "ahmet.sourtimes@gmail.com",
        "department": "Analytics",
        "position": "Medior"
    },
    {
        "id": "901eca94-203e-418e-83bb-49ee94ddab72",
        "firstName": "Ahmet",
        "lastName": "Sourtimes",
        "dateOfBirth": "1973-09-27",
        "dateOfEmployment": "2023-11-01",
        "phoneNumber": "0524-757 5854",
        "email": "ahmet.sourtimes@gmail.com",
        "department": "Analytics",
        "position": "Senior"
    },
    {
        "id": "659a765b-5731-48ad-9532-73818c68bc65",
        "firstName": "Ahmet",
        "lastName": "Sourtimes",
        "dateOfBirth": "1966-09-19",
        "dateOfEmployment": "2023-11-01",
        "phoneNumber": "262 4 835",
        "email": "ahmet.sourtimes@gmail.com",
        "department": "Analytics",
        "position": "Junior"
    },
    {
        "id": "c7b92a7a-562f-4679-9455-ac9188144377",
        "firstName": "Ahmet",
        "lastName": "Sourtimes",
        "dateOfBirth": "1974-03-26",
        "dateOfEmployment": "2023-11-01",
        "phoneNumber": "(304)057 8465",
        "email": "ahmet.sourtimes@gmail.com",
        "department": "Analytics",
        "position": "Junior"
    },
    {
        "id": "1e874a55-5507-499f-8572-9e1fe75baa13",
        "firstName": "Ahmet",
        "lastName": "Sourtimes",
        "dateOfBirth": "1974-03-12",
        "dateOfEmployment": "2023-11-01",
        "phoneNumber": "116 1 086",
        "email": "ahmet.sourtimes@gmail.com",
        "department": "Tech",
        "position": "Medior"
    },
    {
        "id": "714ac31b-155f-4802-9517-0cda3e665b49",
        "firstName": "Ahmet",
        "lastName": "Sourtimes",
        "dateOfBirth": "1970-01-11",
        "dateOfEmployment": "2023-11-01",
        "phoneNumber": "02197795145",
        "email": "ahmet.sourtimes@gmail.com",
        "department": "Analytics",
        "position": "Senior"
    },
    {
        "id": "86fef3d0-1177-4390-9889-92d4eacf693e",
        "firstName": "Ahmet",
        "lastName": "Sourtimes",
        "dateOfBirth": "1971-07-19",
        "dateOfEmployment": "2023-11-01",
        "phoneNumber": "09236778032",
        "email": "ahmet.sourtimes@gmail.com",
        "department": "Analytics",
        "position": "Medior"
    },
    {
        "id": "9c6e8af9-9fca-4832-9b65-24555103ad14",
        "firstName": "Ahmet",
        "lastName": "Sourtimes",
        "dateOfBirth": "1974-09-16",
        "dateOfEmployment": "2023-11-01",
        "phoneNumber": "0931-383 5892",
        "email": "ahmet.sourtimes@gmail.com",
        "department": "Analytics",
        "position": "Senior"
    },
    {
        "id": "dca57429-4d0c-472f-89d5-d669e83d484d",
        "firstName": "Ahmet",
        "lastName": "Sourtimes",
        "dateOfBirth": "1978-10-21",
        "dateOfEmployment": "2023-11-01",
        "phoneNumber": "+90(641)846-6419x4070",
        "email": "ahmet.sourtimes@gmail.com",
        "department": "Analytics",
        "position": "Junior"
    },
    {
        "id": "2f0844fb-4aa7-4973-ab75-19543d715ae9",
        "firstName": "Ahmet",
        "lastName": "Sourtimes",
        "dateOfBirth": "2001-12-24",
        "dateOfEmployment": "2023-11-01",
        "phoneNumber": "+90(538)017-4798x7365",
        "email": "ahmet.sourtimes@gmail.com",
        "department": "Tech",
        "position": "Junior"
    },
    {
        "id": "f01c68e4-cad9-4334-8f86-0de31b1849b2",
        "firstName": "Ahmet",
        "lastName": "Sourtimes",
        "dateOfBirth": "1977-03-23",
        "dateOfEmployment": "2023-11-01",
        "phoneNumber": "0054 939 13 68",
        "email": "ahmet.sourtimes@gmail.com",
        "department": "Tech",
        "position": "Junior"
    },
    {
        "id": "3d6702cf-4194-4df4-9d5b-b80101751563",
        "firstName": "Ahmet",
        "lastName": "Sourtimes",
        "dateOfBirth": "1986-12-04",
        "dateOfEmployment": "2023-11-01",
        "phoneNumber": "0699 688 07 93",
        "email": "ahmet.sourtimes@gmail.com",
        "department": "Analytics",
        "position": "Junior"
    },
    {
        "id": "01256981-311a-4f13-9c6e-adf3d8aeb45d",
        "firstName": "Ahmet",
        "lastName": "Sourtimes",
        "dateOfBirth": "2002-11-29",
        "dateOfEmployment": "2023-11-01",
        "phoneNumber": "01548665260",
        "email": "ahmet.sourtimes@gmail.com",
        "department": "Tech",
        "position": "Junior"
    },
    {
        "id": "31ba4350-ca0a-4263-92ab-78066f31d695",
        "firstName": "Ahmet",
        "lastName": "Sourtimes",
        "dateOfBirth": "2000-01-09",
        "dateOfEmployment": "2023-11-01",
        "phoneNumber": "(182)316 5152",
        "email": "ahmet.sourtimes@gmail.com",
        "department": "Analytics",
        "position": "Medior"
    },
    {
        "id": "",
        "firstName": "Ahmet",
        "lastName": "Sourtimes",
        "dateOfBirth": "1964-08-02",
        "dateOfEmployment": "2023-11-01",
        "phoneNumber": "+90(081)276-1679x9752",
        "email": "ahmet.sourtimes@gmail.com",
        "department": "Analytics",
        "position": "Junior"
    },
    {
        "id": "52ea6f62-cb11-4327-bf41-f7576bac3c89",
        "firstName": "Crystal",
        "lastName": "Walters",
        "dateOfBirth": "1987-08-16",
        "dateOfEmployment": "2024-02-07",
        "phoneNumber": "402.319.5467x437",
        "email": "pwilliams@yahoo.com",
        "department": "Analytics",
        "position": "Senior"
    },
    {
        "id": "948b4e00-c42e-496c-9464-03df6b35470c",
        "firstName": "John",
        "lastName": "Lewis",
        "dateOfBirth": "1979-07-25",
        "dateOfEmployment": "2024-11-17",
        "phoneNumber": "248-514-3174x6501",
        "email": "robert98@yahoo.com",
        "department": "Tech",
        "position": "Medior"
    },
    {
        "id": "6666d8e3-2eb9-4cc2-86fe-a90aa387de04",
        "firstName": "Bryan",
        "lastName": "Weber",
        "dateOfBirth": "1989-04-13",
        "dateOfEmployment": "2024-10-22",
        "phoneNumber": "504.076.5853",
        "email": "wilcoxdavid@gmail.com",
        "department": "Analytics",
        "position": "Senior"
    },
    {
        "id": "7bea43f2-d925-4e3d-a4c3-722782614448",
        "firstName": "Kirsten",
        "lastName": "Miranda",
        "dateOfBirth": "1996-04-09",
        "dateOfEmployment": "2024-08-21",
        "phoneNumber": "+1-226-862-2636x646",
        "email": "pweeks@sandoval.com",
        "department": "Tech",
        "position": "Medior"
    },
    {
        "id": "88af5bce-356d-48ef-adaf-b9cf3e4731fb",
        "firstName": "Cesar",
        "lastName": "Nelson",
        "dateOfBirth": "1996-03-07",
        "dateOfEmployment": "2024-10-25",
        "phoneNumber": "(389)827-3376x381",
        "email": "susanallen@mitchell.com",
        "department": "Analytics",
        "position": "Medior"
    },
    {
        "id": "b0e2de40-dc73-411e-b8ab-22aac6d98538",
        "firstName": "Felicia",
        "lastName": "Sanders",
        "dateOfBirth": "2004-07-23",
        "dateOfEmployment": "2024-08-06",
        "phoneNumber": "581.413.9977x485",
        "email": "francisco95@harris.biz",
        "department": "Tech",
        "position": "Medior"
    },
    {
        "id": "81ceb002-c164-4d7c-92cc-22e38a13bd29",
        "firstName": "Lindsey",
        "lastName": "Farley",
        "dateOfBirth": "1977-04-17",
        "dateOfEmployment": "2024-03-04",
        "phoneNumber": "8788836985",
        "email": "zacharysanchez@smith.com",
        "department": "Analytics",
        "position": "Junior"
    },
    {
        "id": "1ccda998-fd96-4302-8353-11e380fae327",
        "firstName": "Lindsey",
        "lastName": "Jones",
        "dateOfBirth": "2004-04-28",
        "dateOfEmployment": "2024-07-29",
        "phoneNumber": "+1-029-958-8460x82008",
        "email": "jerrystanton@gmail.com",
        "department": "Analytics",
        "position": "Senior"
    },
    {
        "id": "d583b1bd-a747-4a89-8d9f-c5a153f3f2a4",
        "firstName": "Casey",
        "lastName": "Banks",
        "dateOfBirth": "1992-10-26",
        "dateOfEmployment": "2024-10-04",
        "phoneNumber": "(224)971-9476",
        "email": "clarkdaniel@thompson.biz",
        "department": "Tech",
        "position": "Junior"
    },
    {
        "id": "d8c7a82f-9d0a-4a4d-b102-0b65f19e3435",
        "firstName": "Whitney",
        "lastName": "Vega",
        "dateOfBirth": "1988-11-14",
        "dateOfEmployment": "2024-02-16",
        "phoneNumber": "225-948-5455",
        "email": "teresawest@gmail.com",
        "department": "Tech",
        "position": "Junior"
    },
    {
        "id": "16f2fa13-0424-417f-b642-41aa0264ac27",
        "firstName": "Brian",
        "lastName": "Lane",
        "dateOfBirth": "1988-12-10",
        "dateOfEmployment": "2024-02-27",
        "phoneNumber": "707.188.1408",
        "email": "jerrycook@garcia-cook.com",
        "department": "Analytics",
        "position": "Medior"
    },
    {
        "id": "3ac25cbb-43ed-4699-aafb-9d1ff76c2b23",
        "firstName": "Ryan",
        "lastName": "Freeman",
        "dateOfBirth": "1983-09-30",
        "dateOfEmployment": "2024-11-15",
        "phoneNumber": "(582)072-5996x9843",
        "email": "wphillips@anderson-jackson.com",
        "department": "Analytics",
        "position": "Senior"
    },
    {
        "id": "00efa7a3-e446-43a7-af5b-f0e6a560f935",
        "firstName": "Lauren",
        "lastName": "Raymond",
        "dateOfBirth": "1986-10-02",
        "dateOfEmployment": "2024-04-07",
        "phoneNumber": "393.782.3928",
        "email": "pamela92@johnston.com",
        "department": "Analytics",
        "position": "Junior"
    },
    {
        "id": "66f053b1-9f0e-4409-a49e-904a30b347a5",
        "firstName": "Jessica",
        "lastName": "Davis",
        "dateOfBirth": "2001-02-02",
        "dateOfEmployment": "2024-11-07",
        "phoneNumber": "4803764149",
        "email": "loriayala@fields-martinez.info",
        "department": "Analytics",
        "position": "Senior"
    },
    {
        "id": "40066e5c-ed77-4032-8dde-d219798de3bf",
        "firstName": "Holly",
        "lastName": "Molina",
        "dateOfBirth": "1975-05-20",
        "dateOfEmployment": "2024-12-04",
        "phoneNumber": "(286)484-1178x36548",
        "email": "qnichols@yahoo.com",
        "department": "Tech",
        "position": "Junior"
    },
    {
        "id": "538d47c5-9fd0-485c-97e3-cb0c78c4a9b8",
        "firstName": "Katrina",
        "lastName": "Dominguez",
        "dateOfBirth": "1991-01-25",
        "dateOfEmployment": "2024-11-07",
        "phoneNumber": "202-102-0894",
        "email": "tcole@lewis-day.com",
        "department": "Tech",
        "position": "Medior"
    },
    {
        "id": "9a28300c-9b50-4696-bc8f-b389ffc8a69f",
        "firstName": "Beth",
        "lastName": "Williamson",
        "dateOfBirth": "1996-06-29",
        "dateOfEmployment": "2024-01-21",
        "phoneNumber": "(054)539-3151",
        "email": "garciascott@frazier.com",
        "department": "Analytics",
        "position": "Senior"
    },
    {
        "id": "f8de64fc-0f59-4638-aa95-4d353851fa2d",
        "firstName": "Melissa",
        "lastName": "Jefferson",
        "dateOfBirth": "2002-09-04",
        "dateOfEmployment": "2024-08-06",
        "phoneNumber": "801-290-9925",
        "email": "larry08@hotmail.com",
        "department": "Tech",
        "position": "Junior"
    },
    {
        "id": "3d27f54e-3499-4cc2-9416-2cc5899e8bd8",
        "firstName": "Christine",
        "lastName": "Holmes",
        "dateOfBirth": "1993-08-21",
        "dateOfEmployment": "2024-08-03",
        "phoneNumber": "2759431355",
        "email": "uvelasquez@snyder.com",
        "department": "Analytics",
        "position": "Senior"
    },
    {
        "id": "3ca869f8-8d06-4f40-a992-05ef933babe4",
        "firstName": "Marcus",
        "lastName": "Olson",
        "dateOfBirth": "1993-12-24",
        "dateOfEmployment": "2024-02-04",
        "phoneNumber": "(701)206-5096x646",
        "email": "kevin94@gmail.com",
        "department": "Analytics",
        "position": "Junior"
    },
    {
        "id": "21658f4d-25aa-43c0-ab03-a8bc2e1c7a5e",
        "firstName": "Dawn",
        "lastName": "Weaver",
        "dateOfBirth": "1979-11-12",
        "dateOfEmployment": "2024-04-26",
        "phoneNumber": "(900)045-7395x308",
        "email": "haley21@gilmore-russo.com",
        "department": "Tech",
        "position": "Junior"
    },
    {
        "id": "db400b49-5f5e-41e1-96bc-b7c038a44da5",
        "firstName": "Deborah",
        "lastName": "Huerta",
        "dateOfBirth": "2003-12-01",
        "dateOfEmployment": "2024-09-16",
        "phoneNumber": "559.736.8194",
        "email": "tyler42@gmail.com",
        "department": "Tech",
        "position": "Medior"
    },
    {
        "id": "b275815b-2736-4ec4-9644-edd3ac0de8b2",
        "firstName": "Michelle",
        "lastName": "Cummings",
        "dateOfBirth": "1988-12-07",
        "dateOfEmployment": "2024-03-13",
        "phoneNumber": "+1-833-780-5171x610",
        "email": "sierraortiz@harding.com",
        "department": "Tech",
        "position": "Junior"
    },
    {
        "id": "3e333dbe-fa09-4f84-8916-e485b98b8006",
        "firstName": "Bryan",
        "lastName": "Turner",
        "dateOfBirth": "1980-04-13",
        "dateOfEmployment": "2024-09-01",
        "phoneNumber": "309-264-3759x79692",
        "email": "rturner@moreno-wolfe.com",
        "department": "Tech",
        "position": "Medior"
    },
    {
        "id": "e6028ec2-5b2e-4531-ab6e-2f5fa4333349",
        "firstName": "Shannon",
        "lastName": "Hernandez",
        "dateOfBirth": "1980-09-11",
        "dateOfEmployment": "2024-12-04",
        "phoneNumber": "+1-256-990-4782x153",
        "email": "sarah39@gmail.com",
        "department": "Tech",
        "position": "Medior"
    },
    {
        "id": "e7b28cf3-a682-451e-9025-38d5f874f0a1",
        "firstName": "Brian",
        "lastName": "Guzman",
        "dateOfBirth": "1977-03-31",
        "dateOfEmployment": "2024-01-25",
        "phoneNumber": "924-137-0566x3650",
        "email": "william91@hotmail.com",
        "department": "Tech",
        "position": "Medior"
    },
    {
        "id": "ce965b8d-cf01-4d17-98bd-a8c2feeaef06",
        "firstName": "Kendra",
        "lastName": "Martinez",
        "dateOfBirth": "1996-08-10",
        "dateOfEmployment": "2024-05-17",
        "phoneNumber": "(438)380-9078x27566",
        "email": "briana41@young.com",
        "department": "Tech",
        "position": "Medior"
    },
    {
        "id": "0907554e-27bf-4db7-a8a3-c0ec094b29a6",
        "firstName": "Lisa",
        "lastName": "Watts",
        "dateOfBirth": "1977-06-30",
        "dateOfEmployment": "2024-01-09",
        "phoneNumber": "961-309-2316x390",
        "email": "srubio@gmail.com",
        "department": "Tech",
        "position": "Medior"
    },
    {
        "id": "bbd08e88-194b-4ada-8f70-2be21adfac4c",
        "firstName": "Jeffrey",
        "lastName": "Jones",
        "dateOfBirth": "1999-11-08",
        "dateOfEmployment": "2024-08-11",
        "phoneNumber": "001-758-848-5881",
        "email": "michele92@williams-martin.net",
        "department": "Analytics",
        "position": "Medior"
    },
    {
        "id": "86d25e8b-0137-4803-8dc2-c7f9f52cc89b",
        "firstName": "Denise",
        "lastName": "Henderson",
        "dateOfBirth": "1985-10-13",
        "dateOfEmployment": "2024-01-04",
        "phoneNumber": "633-611-5815x768",
        "email": "richard31@yahoo.com",
        "department": "Analytics",
        "position": "Senior"
    },
    {
        "id": "9915e56f-8eae-43fc-892d-65da9c565b43",
        "firstName": "Lori",
        "lastName": "Scott",
        "dateOfBirth": "1998-12-10",
        "dateOfEmployment": "2024-06-04",
        "phoneNumber": "(732)106-6862x87286",
        "email": "sullivanjoshua@oconnell.com",
        "department": "Tech",
        "position": "Junior"
    },
    {
        "id": "bfeee294-a681-451d-8876-6488309c08cf",
        "firstName": "Jennifer",
        "lastName": "Rasmussen",
        "dateOfBirth": "1983-03-22",
        "dateOfEmployment": "2024-02-23",
        "phoneNumber": "+1-283-240-6765",
        "email": "pstevenson@yahoo.com",
        "department": "Tech",
        "position": "Medior"
    },
    {
        "id": "480fd296-136d-4ecf-8439-fc420237d247",
        "firstName": "Kayla",
        "lastName": "Allen",
        "dateOfBirth": "1976-10-22",
        "dateOfEmployment": "2024-05-02",
        "phoneNumber": "+1-394-591-4203x78374",
        "email": "matthewbarajas@haas-flores.com",
        "department": "Analytics",
        "position": "Medior"
    },
    {
        "id": "61b7c691-1e48-4e50-8ca4-4fcbc0b777ad",
        "firstName": "Jessica",
        "lastName": "Mcintosh",
        "dateOfBirth": "1998-07-12",
        "dateOfEmployment": "2024-09-07",
        "phoneNumber": "001-843-051-4613x9162",
        "email": "brooke65@yahoo.com",
        "department": "Analytics",
        "position": "Senior"
    },
    {
        "id": "3231dd4a-c18b-4b3c-974c-f4a9cb7e6964",
        "firstName": "Katherine",
        "lastName": "Roy",
        "dateOfBirth": "1976-04-20",
        "dateOfEmployment": "2024-03-26",
        "phoneNumber": "479.332.5983x40676",
        "email": "jonespaula@lee-mahoney.biz",
        "department": "Tech",
        "position": "Junior"
    },
    {
        "id": "fb99b355-1e69-44bc-bd58-653ded20b771",
        "firstName": "Melanie",
        "lastName": "Mack",
        "dateOfBirth": "1985-11-25",
        "dateOfEmployment": "2024-11-29",
        "phoneNumber": "000.397.0888",
        "email": "lindahernandez@gmail.com",
        "department": "Analytics",
        "position": "Medior"
    },
    {
        "id": "55410372-c042-4d0d-b605-412d9bfbb751",
        "firstName": "Courtney",
        "lastName": "Brooks",
        "dateOfBirth": "1996-02-19",
        "dateOfEmployment": "2024-06-13",
        "phoneNumber": "923.723.0193",
        "email": "julie26@yahoo.com",
        "department": "Tech",
        "position": "Medior"
    },
    {
        "id": "e9fce33e-0cad-4b7b-a3df-5c3d58f016e8",
        "firstName": "Nathan",
        "lastName": "Schultz",
        "dateOfBirth": "2001-03-03",
        "dateOfEmployment": "2024-09-03",
        "phoneNumber": "+1-582-202-6729x983",
        "email": "tjones@yahoo.com",
        "department": "Tech",
        "position": "Junior"
    },
    {
        "id": "b7c66cd3-794b-4e6e-ad67-caac23e6dcbd",
        "firstName": "Gregory",
        "lastName": "Singh",
        "dateOfBirth": "1977-08-12",
        "dateOfEmployment": "2024-07-07",
        "phoneNumber": "665.413.8682x5264",
        "email": "richardcox@gmail.com",
        "department": "Analytics",
        "position": "Junior"
    },
    {
        "id": "18ed2a80-0d6c-4213-a7a5-5c302ce9f9f4",
        "firstName": "Patrick",
        "lastName": "Garcia",
        "dateOfBirth": "1986-08-20",
        "dateOfEmployment": "2024-09-06",
        "phoneNumber": "(461)232-3944",
        "email": "stephenmay@sherman-richardson.com",
        "department": "Analytics",
        "position": "Medior"
    },
    {
        "id": "2d875c43-a64a-42cf-abdd-4a3894d46181",
        "firstName": "Jeffrey",
        "lastName": "Baker",
        "dateOfBirth": "1998-05-20",
        "dateOfEmployment": "2024-02-10",
        "phoneNumber": "146.706.8698x54026",
        "email": "eric79@hotmail.com",
        "department": "Tech",
        "position": "Medior"
    },
    {
        "id": "a54cfb3d-64a7-455b-8ccf-73bfe41f6c51",
        "firstName": "Tony",
        "lastName": "Blanchard",
        "dateOfBirth": "1996-07-29",
        "dateOfEmployment": "2024-11-01",
        "phoneNumber": "846-245-2518",
        "email": "graypaula@curtis-wade.org",
        "department": "Tech",
        "position": "Junior"
    },
    {
        "id": "43406b63-8430-4f2c-b3ca-a3b28363f978",
        "firstName": "Jason",
        "lastName": "Wheeler",
        "dateOfBirth": "1978-06-23",
        "dateOfEmployment": "2024-04-10",
        "phoneNumber": "001-196-902-1363",
        "email": "monica29@gmail.com",
        "department": "Tech",
        "position": "Senior"
    },
    {
        "id": "bac112e3-6784-425f-9afc-10586f075696",
        "firstName": "Diane",
        "lastName": "King",
        "dateOfBirth": "1997-07-11",
        "dateOfEmployment": "2024-02-19",
        "phoneNumber": "+1-989-662-5861x0570",
        "email": "emurphy@nelson.com",
        "department": "Tech",
        "position": "Medior"
    },
    {
        "id": "045897fb-2621-40e0-a0bf-b3820f8294f1",
        "firstName": "Evan",
        "lastName": "Strickland",
        "dateOfBirth": "1976-07-05",
        "dateOfEmployment": "2024-11-29",
        "phoneNumber": "001-152-629-9206x439",
        "email": "tracie28@gmail.com",
        "department": "Analytics",
        "position": "Medior"
    },
    {
        "id": "0a996e80-3e3f-42b3-9e12-a3540aac510a",
        "firstName": "Felicia",
        "lastName": "Black",
        "dateOfBirth": "2002-04-01",
        "dateOfEmployment": "2024-10-26",
        "phoneNumber": "129.876.4966",
        "email": "kmorales@gmail.com",
        "department": "Tech",
        "position": "Senior"
    },
    {
        "id": "b3aba35a-a75e-431a-9c2b-498d8da84394",
        "firstName": "Jasmine",
        "lastName": "Williams",
        "dateOfBirth": "2002-02-14",
        "dateOfEmployment": "2024-06-23",
        "phoneNumber": "540-219-0007x96854",
        "email": "umitchell@yahoo.com",
        "department": "Tech",
        "position": "Medior"
    },
    {
        "id": "198b525f-8fd3-47ec-8b11-dae0e73e0563",
        "firstName": "Maria",
        "lastName": "Glover",
        "dateOfBirth": "1986-12-29",
        "dateOfEmployment": "2024-02-13",
        "phoneNumber": "964-649-5747",
        "email": "kirbysamuel@wade-mathews.com",
        "department": "Tech",
        "position": "Medior"
    },
    {
        "id": "6f3f7dcc-3a69-4d66-8ac3-d8952fd509a3",
        "firstName": "Mark",
        "lastName": "Moore",
        "dateOfBirth": "1978-02-23",
        "dateOfEmployment": "2024-03-03",
        "phoneNumber": "(428)936-4447x6042",
        "email": "matthewsjennifer@yahoo.com",
        "department": "Analytics",
        "position": "Senior"
    },
    {
        "id": "02c57e44-c422-436f-b13f-54aed9cb8e65",
        "firstName": "Rachel",
        "lastName": "Herrera",
        "dateOfBirth": "1985-09-21",
        "dateOfEmployment": "2024-09-16",
        "phoneNumber": "953-895-7448x668",
        "email": "jeffery12@lawrence.com",
        "department": "Tech",
        "position": "Junior"
    }
]